<?xml version="1.0" encoding="UTF-8"?>
<objects serializationModel="Studio.02.01.00">
	<object class="MixerGroup" id="{f77aee74-cb9b-4df7-8b3f-659909051762}">
		<property name="name">
			<value>Master</value>
		</property>
		<relationship name="effectChain">
			<destination>{f56e51dd-f647-4e74-af0e-6d21620696aa}</destination>
		</relationship>
		<relationship name="panner">
			<destination>{23578f23-fb8d-425c-bd5f-91a4e3acdbc8}</destination>
		</relationship>
		<relationship name="output">
			<destination>{3c980ee9-291e-4abe-898c-d0279e641a08}</destination>
		</relationship>
	</object>
	<object class="MixerBusEffectChain" id="{f56e51dd-f647-4e74-af0e-6d21620696aa}">
		<relationship name="effects">
			<destination>{e6cecd4c-803c-4d2d-b78d-f82641541666}</destination>
		</relationship>
	</object>
	<object class="MixerBusPanner" id="{23578f23-fb8d-425c-bd5f-91a4e3acdbc8}" />
	<object class="MixerBusFader" id="{e6cecd4c-803c-4d2d-b78d-f82641541666}" />
</objects>
